snake_me_please/__init__.py
snake_me_please/converter.py
snake_me_please-0.8.dist-info/LICENSE
snake_me_please-0.8.dist-info/METADATA
snake_me_please-0.8.dist-info/WHEEL
snake_me_please-0.8.dist-info/entry_points.txt
snake_me_please-0.8.dist-info/top_level.txt
snake_me_please-0.8.dist-info/RECORD
