Metadata-Version: 2.1
Name: snake_me_please
Version: 0.8
Summary: Snake Me Please is a Python package and command-line tool designed to convert user-defined variable names to snake_case in Python files while excluding imported variables and keywords from Python libraries.
Home-page: https://github.com/AdityaJ7/snake_me_please
Author: Aditya Jetely
Author-email: ajetely@gmail.com
License: public
License-File: LICENSE
